setup.py
txGraylog.egg-info/PKG-INFO
txGraylog.egg-info/SOURCES.txt
txGraylog.egg-info/dependency_links.txt
txGraylog.egg-info/not-zip-safe
txGraylog.egg-info/requires.txt
txGraylog.egg-info/top_level.txt
txgraylog/__init__.py
txgraylog/observer.py
txgraylog/service.py
txgraylog/protocol/__init__.py
txgraylog/protocol/gelf.py
txgraylog/protocol/tcp.py
txgraylog/protocol/udp.py
txgraylog/test/__init__.py
txgraylog/test/test_gelf.py