Metadata-Version: 1.1
Name: txGraylog
Version: 0.3
Summary: A twisted log service that interacts with Graylog2.
Home-page: https://github.com/dr4ke616/txGraylog/
Author: Adam Drakeford
Author-email: adamdrakeford@gmail.com
License: MIT
Platform: UNKNOWN
Classifier: Framework :: Twisted
Classifier: Intended Audience :: Developers
Classifier: Operating System :: POSIX :: Linux
Classifier: Programming Language :: Python
Classifier: Programming Language :: Python :: 2.7
Classifier: Programming Language :: Python :: Implementation :: CPython
Classifier: Topic :: System :: Logging
Classifier: Topic :: Software Development
Classifier: Topic :: Software Development :: Libraries
Classifier: Topic :: Software Development :: Libraries :: Python Modules
Requires: twisted(>=10.2.0)
